{
  "footerGroups": [
    { "id": "overview", "labelKey": "group-overview", "order": 10, "enabled": true },
    { "id": "guidelines", "labelKey": "group-guidelines", "order": 20, "enabled": true },
    { "id": "submission", "labelKey": "group-submission", "order": 30, "enabled": true },
    { "id": "usage", "labelKey": "group-usage", "order": 40, "enabled": true },
    { "id": "policy", "labelKey": "group-policy", "order": 50, "enabled": true }
  ],
  "items": [
    { "id": "home", "footer": { "enabled": true, "groupId": "overview", "order": 10 } },
    {
      "id": "data-submission",
      "navbar": { "enabled": true, "visibility": "essential", "order": 10 },
      "footer": { "enabled": true, "groupId": "submission", "order": 10 }
    },
    {
      "id": "application",
      "parentId": "data-submission",
      "navbar": { "enabled": true, "visibility": "secondary", "order": 10 },
      "footer": { "enabled": true, "groupId": "submission", "order": 20 }
    },
    {
      "id": "guidelines",
      "navbar": { "enabled": true, "visibility": "essential", "order": 20 },
      "footer": { "enabled": true, "groupId": "guidelines", "order": 10 }
    },
    {
      "id": "data-sharing-guidelines",
      "parentId": "guidelines",
      "navbar": { "enabled": true, "visibility": "secondary", "order": 10 },
      "footer": { "enabled": true, "groupId": "guidelines", "order": 20 }
    },
    {
      "id": "security-guidelines-for-users",
      "parentId": "guidelines",
      "navbar": { "enabled": true, "visibility": "secondary", "order": 20 },
      "footer": { "enabled": true, "groupId": "guidelines", "order": 30 }
    },
    {
      "id": "security-guidelines-for-submitters",
      "parentId": "guidelines",
      "navbar": { "enabled": true, "visibility": "secondary", "order": 30 },
      "footer": { "enabled": true, "groupId": "guidelines", "order": 40 }
    },
    {
      "id": "security-guidelines-for-dbcenters",
      "parentId": "guidelines",
      "navbar": { "enabled": true, "visibility": "secondary", "order": 40 },
      "footer": { "enabled": true, "groupId": "guidelines", "order": 50 }
    },
    {
      "id": "data-usage",
      "navbar": { "enabled": true, "visibility": "essential", "order": 30 },
      "footer": { "enabled": true, "groupId": "usage", "order": 10 }
    },
    {
      "id": "research-list",
      "parentId": "data-usage",
      "navbar": { "enabled": true, "visibility": "secondary", "order": 10 },
      "footer": { "enabled": true, "groupId": "usage", "order": 20 }
    },
    {
      "id": "dataset-list",
      "parentId": "data-usage",
      "navbar": { "enabled": true, "visibility": "secondary", "order": 20 },
      "footer": { "enabled": true, "groupId": "usage", "order": 30 }
    },
    {
      "id": "data-processing",
      "navbar": { "enabled": true, "visibility": "essential", "order": 40 },
      "footer": { "enabled": true, "groupId": "usage", "order": 40 }
    },
    {
      "id": "off-premise-server",
      "navbar": { "enabled": true, "visibility": "essential", "order": 50 },
      "footer": { "enabled": true, "groupId": "policy", "order": 20 }
    },
    {
      "id": "dac",
      "navbar": { "enabled": true, "visibility": "essential", "order": 60 },
      "footer": { "enabled": true, "groupId": "submission", "order": 40 }
    },
    {
      "id": "publications",
      "navbar": { "enabled": true, "visibility": "essential", "order": 70 },
      "footer": { "enabled": true, "groupId": "overview", "order": 70 }
    },
    {
      "id": "violation",
      "navbar": { "enabled": true, "visibility": "essential", "order": 80 },
      "footer": { "enabled": true, "groupId": "policy", "order": 40 }
    },
    {
      "id": "privacy-policy",
      "navbar": { "enabled": true, "visibility": "essential", "order": 90 },
      "footer": { "enabled": true, "groupId": "policy", "order": 50 }
    },
    {
      "id": "faq",
      "navbar": { "enabled": true, "visibility": "essential", "order": 100 },
      "footer": { "enabled": true, "groupId": "overview", "order": 80 }
    },
    {
      "id": "supported-browsers",
      "footer": { "enabled": true, "groupId": "policy", "order": 60 }
    }
  ]
}
