{
  "mappings": {
    "dynamic": false,
    "properties": {
      "datasetId": {
        "type": "keyword"
      },
      "version": {
        "type": "keyword"
      },
      "versionReleaseDate": {
        "type": "keyword"
      },
      "humId": {
        "type": "keyword"
      },
      "humVersionId": {
        "type": "keyword"
      },
      "typeOfData": {
        "type": "object",
        "properties": {
          "ja": {
            "type": "keyword"
          },
          "en": {
            "type": "keyword"
          }
        }
      },
      "criteria": {
        "type": "keyword"
      },
      "releaseDate": {
        "type": "keyword"
      },
      "searchable": {
        "properties": {
          "diseases": {
            "type": "nested",
            "properties": {
              "label": {
                "type": "keyword"
              },
              "icd10": {
                "type": "keyword"
              }
            }
          },
          "tissues": {
            "type": "keyword"
          },
          "assayTypes": {
            "type": "keyword"
          },
          "platforms": {
            "type": "nested",
            "properties": {
              "vendor": {
                "type": "keyword"
              },
              "model": {
                "type": "keyword"
              }
            }
          },
          "readTypes": {
            "type": "keyword"
          },
          "fileTypes": {
            "type": "keyword"
          },
          "totalSubjectCount": {
            "type": "integer"
          },
          "totalDataVolumeBytes": {
            "type": "long"
          },
          "hasHealthyControl": {
            "type": "boolean"
          },
          "hasTumor": {
            "type": "boolean"
          },
          "hasCellLine": {
            "type": "boolean"
          }
        }
      },
      "experiments": {
        "type": "nested",
        "properties": {
          "experimentKey": {
            "type": "keyword"
          },
          "matchType": {
            "type": "keyword"
          },
          "header": {
            "type": "object",
            "properties": {
              "ja": {
                "type": "object",
                "properties": {
                  "text": {
                    "type": "text",
                    "fields": {
                      "kw": {
                        "type": "keyword"
                      }
                    }
                  },
                  "rawHtml": {
                    "type": "text",
                    "index": false
                  }
                }
              },
              "en": {
                "type": "object",
                "properties": {
                  "text": {
                    "type": "text",
                    "fields": {
                      "kw": {
                        "type": "keyword"
                      }
                    }
                  },
                  "rawHtml": {
                    "type": "text",
                    "index": false
                  }
                }
              }
            }
          },
          "data": {
            "type": "flattened"
          },
          "footers": {
            "type": "object",
            "properties": {
              "ja": {
                "type": "object",
                "properties": {
                  "text": {
                    "type": "text"
                  },
                  "rawHtml": {
                    "type": "text",
                    "index": false
                  }
                }
              },
              "en": {
                "type": "object",
                "properties": {
                  "text": {
                    "type": "text"
                  },
                  "rawHtml": {
                    "type": "text",
                    "index": false
                  }
                }
              }
            }
          },
          "extracted": {
            "properties": {
              "subjectCount": {
                "type": "integer"
              },
              "subjectCountType": {
                "type": "keyword"
              },
              "healthStatus": {
                "type": "keyword"
              },
              "disease": {
                "properties": {
                  "label": {
                    "type": "keyword"
                  },
                  "icd10": {
                    "type": "keyword"
                  }
                }
              },
              "tissue": {
                "type": "keyword"
              },
              "isTumor": {
                "type": "boolean"
              },
              "cellLine": {
                "type": "keyword"
              },
              "assayType": {
                "type": "keyword"
              },
              "libraryKit": {
                "type": "text"
              },
              "platformVendor": {
                "type": "keyword"
              },
              "platformModel": {
                "type": "keyword"
              },
              "readType": {
                "type": "keyword"
              },
              "readLength": {
                "type": "integer"
              },
              "targets": {
                "type": "text"
              },
              "fileTypes": {
                "type": "keyword"
              },
              "dataVolumeBytes": {
                "type": "long"
              }
            }
          }
        }
      }
    }
  }
}
